bellybuttonseg/BBHP_function.py
bellybuttonseg/DataGenerator.py
bellybuttonseg/__init__.py
bellybuttonseg/createdir.py
bellybuttonseg/example1.py
bellybuttonseg/example2.py
bellybuttonseg/example3.py
bellybuttonseg/generate_network.py
bellybuttonseg/load_save_helpers.py
bellybuttonseg/newproject.py
bellybuttonseg/predict.py
bellybuttonseg/saved_model_functions.py
bellybuttonseg/train.py
bellybuttonseg/trainandpredict.py
bellybuttonseg-0.0.31.dist-info/LICENSE.txt
bellybuttonseg-0.0.31.dist-info/METADATA
bellybuttonseg-0.0.31.dist-info/WHEEL
bellybuttonseg-0.0.31.dist-info/top_level.txt
bellybuttonseg-0.0.31.dist-info/RECORD
