Metadata-Version: 2.1
Name: bellybuttonseg
Version: 0.0.31
Summary: An easy-to-use image segmentation package
Author-email: Sam Dillavou <sam.dillavou@gmail.com>, Jesse Hanlan <jhanlan@sas.upenn.edu>
License: MIT License
Project-URL: Homepage, https://github.com/sdillavou/bellybuttonseg
Project-URL: Bug Tracker, https://github.com/sdillavou/bellybuttonseg/issues
Classifier: Programming Language :: Python :: 3
Classifier: License :: OSI Approved :: MIT License
Classifier: Operating System :: OS Independent
Requires-Python: >=3.7
License-File: LICENSE.txt
Requires-Dist: numpy
Requires-Dist: matplotlib
Requires-Dist: opencv-contrib-python ==4.5.5.64
Requires-Dist: scipy
Requires-Dist: scikit-image
Requires-Dist: pillow
Requires-Dist: requests
